permutation/__init__.py
permutation/py.typed
permutation-0.5.0.dist-info/METADATA
permutation-0.5.0.dist-info/WHEEL
permutation-0.5.0.dist-info/licenses/LICENSE
permutation-0.5.0.dist-info/RECORD
