Metadata-Version: 2.3
Name: permutation
Version: 0.5.0
Summary: Permutations of finitely many positive integers
Project-URL: Source Code, https://github.com/jwodder/permutation
Project-URL: Bug Tracker, https://github.com/jwodder/permutation/issues
Project-URL: Documentation, https://permutation.readthedocs.io
Author-email: John Thorvald Wodder II <permutation@varonathe.org>
License: MIT
Keywords: group theory,math,mathematics,maths,permutation,symmetric group
Classifier: Intended Audience :: Developers
Classifier: License :: OSI Approved :: MIT License
Classifier: Programming Language :: Python :: 3
Classifier: Programming Language :: Python :: 3 :: Only
Classifier: Programming Language :: Python :: 3.8
Classifier: Programming Language :: Python :: 3.9
Classifier: Programming Language :: Python :: 3.10
Classifier: Programming Language :: Python :: 3.11
Classifier: Programming Language :: Python :: 3.12
Classifier: Programming Language :: Python :: 3.13
Classifier: Programming Language :: Python :: Implementation :: CPython
Classifier: Programming Language :: Python :: Implementation :: PyPy
Classifier: Topic :: Scientific/Engineering :: Mathematics
Classifier: Typing :: Typed
Requires-Python: >=3.8
